argus/__init__.py
argus/_version.py
argus/client/__init__.py
argus/client/base.py
argus/client/generic_result.py
argus/client/driver_matrix_tests/cli.py
argus/client/driver_matrix_tests/client.py
argus/client/generic/cli.py
argus/client/generic/client.py
argus/client/sct/client.py
argus/client/sct/types.py
argus/client/sirenada/client.py
argus/common/__init__.py
argus/common/enums.py
argus/common/sct_types.py
argus/common/sirenada_types.py
argus_alm-0.15.7.dist-info/licenses/LICENSE
argus_alm-0.15.7.dist-info/METADATA
argus_alm-0.15.7.dist-info/WHEEL
argus_alm-0.15.7.dist-info/entry_points.txt
argus_alm-0.15.7.dist-info/top_level.txt
argus_alm-0.15.7.dist-info/RECORD
