Metadata-Version: 2.4
Name: argus-alm
Version: 0.15.7
Summary: Argus
Author-email: Alexey Kartashov <alexey.kartashov@scylladb.com>, Łukasz Sójka <lukasz.sojka@scylladb.com>
License-Expression: Apache-2.0
Project-URL: Homepage, https://github.com/scylladb/argus
Project-URL: Repository, https://github.com/scylladb/argus
Requires-Python: >=3.12
License-File: LICENSE
Requires-Dist: requests>=2.26.0
Requires-Dist: click>=8.1.3
Provides-Extra: web-backend
Requires-Dist: PyYAML~=6.0.0; extra == "web-backend"
Requires-Dist: scylla-driver>=3.26.8; extra == "web-backend"
Requires-Dist: Flask~=3.0.0; extra == "web-backend"
Requires-Dist: Flask-WTF~=1.0.0; extra == "web-backend"
Requires-Dist: Flask-Login~=0.5.0; extra == "web-backend"
Requires-Dist: humanize~=3.13.1; extra == "web-backend"
Requires-Dist: python-magic~=0.4.24; extra == "web-backend"
Requires-Dist: uwsgi~=2.0.20; extra == "web-backend"
Requires-Dist: python-jenkins>=1.7.0; extra == "web-backend"
Requires-Dist: python-slugify~=6.1.1; extra == "web-backend"
Requires-Dist: pygithub>=2.6.1; extra == "web-backend"
Requires-Dist: boto3~=1.38.9; extra == "web-backend"
Requires-Dist: prometheus-flask-exporter>=0.23.2; extra == "web-backend"
Provides-Extra: docker-image
Requires-Dist: supervisor~=4.2.4; extra == "docker-image"
Provides-Extra: dev
Requires-Dist: pytest==8.3.5; extra == "dev"
Requires-Dist: coverage==7.8.2; extra == "dev"
Requires-Dist: docker==7.1.0; extra == "dev"
Requires-Dist: ipython~=8.36.0; extra == "dev"
Requires-Dist: pre-commit>=4.2.0; extra == "dev"
Requires-Dist: ruff~=0.11.11; extra == "dev"
Requires-Dist: autopep8>=2.3.2; extra == "dev"
Requires-Dist: requests-mock~=1.12.1; extra == "dev"
Requires-Dist: codecov~=2.1.12; extra == "dev"
Requires-Dist: pytest-cov~=6.1.1; extra == "dev"
Requires-Dist: nox~=2025.5.1; extra == "dev"
Requires-Dist: pytest-xdist~=3.7.0; extra == "dev"
Requires-Dist: pytest-subtests~=0.14.1; extra == "dev"
Requires-Dist: boto3-stubs~=1.38.9; extra == "dev"
Dynamic: license-file
